xcover/__init__.py
xcover/auth.py
xcover/config.py
xcover/encoder.py
xcover/exceptions.py
xcover/utils.py
xcover/xcover.py
xcover_python-0.1.2.dist-info/METADATA
xcover_python-0.1.2.dist-info/WHEEL
xcover_python-0.1.2.dist-info/RECORD
