Metadata-Version: 2.3
Name: xcover-python
Version: 0.1.2
Summary: Python client for XCover API (XCore).
License: MIT
Keywords: xcover,api,api-client,insurance
Author: Artem Kolesnikov
Author-email: artem@covergenius.com
Maintainer: Artem Kolesnikov
Maintainer-email: artem@covergenius.com
Requires-Python: >=3.8,<4.0
Classifier: License :: OSI Approved :: MIT License
Classifier: Programming Language :: Python :: 3
Classifier: Programming Language :: Python :: 3.8
Classifier: Programming Language :: Python :: 3.9
Classifier: Programming Language :: Python :: 3.10
Classifier: Programming Language :: Python :: 3.11
Classifier: Programming Language :: Python :: 3.12
Classifier: Programming Language :: Python :: 3.13
Requires-Dist: requests (>=2.26,<3.0)
Project-URL: Homepage, https://www.covergenius.com/xcover/
Project-URL: Repository, https://github.com/CoverGenius/xcover-python
